pywincontroller/__init__.py
pywincontroller/pywincontroller.py
pywincontroller/utils.py
pywincontroller-1.3.1.dist-info/LICENSE
pywincontroller-1.3.1.dist-info/METADATA
pywincontroller-1.3.1.dist-info/WHEEL
pywincontroller-1.3.1.dist-info/top_level.txt
pywincontroller-1.3.1.dist-info/RECORD
